logilab/constraint/__init__.py
logilab/constraint/distributors.py
logilab/constraint/fd.py
logilab/constraint/fi.py
logilab/constraint/interfaces.py
logilab/constraint/propagation.py
logilab_constraint-1.0.dist-info/COPYING
logilab_constraint-1.0.dist-info/COPYING.LESSER
logilab_constraint-1.0.dist-info/METADATA
logilab_constraint-1.0.dist-info/WHEEL
logilab_constraint-1.0.dist-info/top_level.txt
logilab_constraint-1.0.dist-info/RECORD
