Metadata-Version: 2.1
Name: logilab-constraint
Version: 1.0
Summary: constraints satisfaction solver in Python
Home-page: http://www.logilab.org/projects/logilab-constraint
Author: Alexandre Fayolle
Author-email: contact@logilab.fr
License: LGPL
Classifier: Topic :: Scientific/Engineering
Classifier: Programming Language :: Python
Classifier: Programming Language :: Python :: 2
Classifier: Programming Language :: Python :: 3
License-File: COPYING
License-File: COPYING.LESSER
Requires-Dist: setuptools
Requires-Dist: logilab-common <3.0.0,>=2.0.0
Requires-Dist: six >=1.4.0
Requires-Dist: importlib-metadata ; python_version < "3.10"
